chromato/__init__.py
chromato/constants.py
chromato/convert.py
chromato/operations.py
chromato/parse.py
chromato/spaces.py
chromato/utils.py
chromato/validation.py
chromato-0.5.0.dist-info/LICENSE
chromato-0.5.0.dist-info/WHEEL
chromato-0.5.0.dist-info/METADATA
chromato-0.5.0.dist-info/RECORD
