Metadata-Version: 2.1
Name: chromato
Version: 0.5.0
Summary: 🍅 Fresh color utilities.
Home-page: https://github.com/vikpe/chromato
License: MIT
Keywords: colors,hex,rgb,cmyk,hsl,hsv
Author: Viktor Persson
Author-email: viktor.persson@arcsin.se
Requires-Python: >=3.6.2,<4.0.0
Classifier: Development Status :: 4 - Beta
Classifier: License :: OSI Approved :: MIT License
Classifier: Programming Language :: Python
Classifier: Programming Language :: Python :: 3
Classifier: Programming Language :: Python :: 3.10
Classifier: Programming Language :: Python :: 3.6
Classifier: Programming Language :: Python :: 3.7
Classifier: Programming Language :: Python :: 3.8
Classifier: Programming Language :: Python :: 3.9
Classifier: Topic :: Utilities
Project-URL: Repository, https://github.com/vikpe/chromato
